pybpmn/__init__.py
pybpmn/bpmn_parser.py
pybpmn/bpmn_process.py
pybpmn/component.py
pybpmn/end_event.py
pybpmn/exceptions.py
pybpmn/exclusive_gateway.py
pybpmn/gateway.py
pybpmn/inclusive_gateway.py
pybpmn/parallel_gateway.py
pybpmn/service_task.py
pybpmn/start_event.py
pybpmn/task.py
pybpmn/user_task.py
py_bpmn-0.4.0.dist-info/LICENSE
py_bpmn-0.4.0.dist-info/METADATA
py_bpmn-0.4.0.dist-info/WHEEL
py_bpmn-0.4.0.dist-info/top_level.txt
py_bpmn-0.4.0.dist-info/RECORD
