Metadata-Version: 2.1
Name: py-bpmn
Version: 0.4.0
Summary: A bpmn framework focused on serverless infrastructure
Home-page: https://github.com/vasudevan-palani/pybpmn
Author: Vasudevan Palani
Author-email: vasudevan.palani@gmail.com
License: TBD
License-File: LICENSE
